EasyHTML2023/EH.py
EasyHTML2023/__init__.py
EasyHTML2023-1.0.0.1.dist-info/METADATA
EasyHTML2023-1.0.0.1.dist-info/WHEEL
EasyHTML2023-1.0.0.1.dist-info/top_level.txt
EasyHTML2023-1.0.0.1.dist-info/RECORD
