Metadata-Version: 2.1
Name: EasyHTML2023
Version: 1.0.0.1
Summary: 中文的python HTML解析提取器！
Home-page: https://pypi.org/user/SuiBo/
Author: SuiBo
Author-email: 534047068@qq.com
License: UNKNOWN
Platform: UNKNOWN
